Workbook

Sheet Assumptions
A1: Coast FIRE Retirement Model — Assumptions
A3: Personal
A4: Current age | B4: 34 | C4: As of 2026 (born 1989)
A5: Target retirement age | B5: 55 | C5: When you stop working
A6: SIPP access age | B6: 57 | C6: Earliest UK private pension access (current rules)
A7: State pension age | B7: 67 | C7: Current UK State Pension age
A8: State pension (£/yr, today's terms) | B8: 11500 | C8: Approx full new State Pension, adjust as needed
A9: Life expectancy / plan to age | B9: 90 | C9: Horizon for drawdown sustainability
A11: Growth & Spending
A12: Real investment growth rate (%/yr) | B12: 0.05 | C12: After inflation, applies to ISA/GIA/SIPP
A13: Desired annual retirement spending (£, today's terms) | B13: 45000 | C13: Your target spend in retirement
A14: Safe withdrawal rate — bridge phase (%) | B14: 0.04 | C14: Used implicitly via direct spend-down ages 50-57
A15: Safe withdrawal rate — long retirement (%) | B15: 0.035 | C15: Applied to SIPP pot at 57 for 40yr+ horizon
A17: Starting Balances (Today)
A18: ISA — current balance | B18: 45000 | C18: Stocks & shares ISA
A19: GIA — current balance | B19: 12000 | C19: General investment account
A20: SIPP — account 1 | B20: 38000
A21: SIPP — account 2 | B21: 51000
A22: SIPP — combined total | B22: =B20+B21 -> 257000
A24: Contribution Plan (Annual, while still contributing)
A25: ISA annual contribution while contributing (£) | B25: 20000 | C25: UK ISA allowance is £20,000/yr
A26: ISA — years you plan to contribute | B26: 2 | C26: Set this; see Coast Plan sheet to test different values
A27: GIA annual contribution while contributing (£) | B27: 0 | C27: Optional — extra GIA saving each year
A28: GIA — years you plan to contribute | B28: 0 | C28: Set this; see Coast Plan sheet to test different values
A29: SIPP annual contribution while contributing (£) | B29: 8000 | C29: Net contribution incl. tax relief — capped by your annual allowance
A30: SIPP — years you plan to contribute | B30: 4 | C30: Set this; see Coast Plan sheet to test different values
A32: Note: yellow cells are the ones to experiment with. Change 'years you plan to contribute'
A33: for each account and watch the Projection and Summary sheets update.

Sheet Projection
A1: Year-by-Year Projection — Age 37 to Age 50 (then bridge to 57)
A3: Year | B3: Age | C3: ISA Start | D3: ISA Contrib? | E3: ISA End | F3: GIA Start | G3: GIA Contrib? | H3: GIA End | I3: SIPP Start | J3: SIPP Contrib? | K3: SIPP End
A4: =YEAR(TODAY()) -> 2026 | B4: =Assumptions!$B$4+0 -> 37 | C4: =Assumptions!$B$18 -> 156000 | D4: =IF(0<Assumptions!$B$26,Assumptions!$B$25,0) -> 20000 | E4: =(C4+D4)*(1+Assumptions!$B$12) -> 184800 | F4: =Assumptions!$B$19 -> 60000 | G4: =IF(0<Assumptions!$B$28,Assumptions!$B$27,0) -> 0 | H4: =(F4+G4)*(1+Assumptions!$B$12) -> 63000 | I4: =Assumptions!$B$22 -> 257000 | J4: =IF(0<Assumptions!$B$30,Assumptions!$B$29,0) -> 10000 | K4: =(I4+J4)*(1+Assumptions!$B$12) -> 280350
A5: =YEAR(TODAY())+1 -> 2027 | B5: =Assumptions!$B$4+1 -> 38 | C5: =E4 -> 184800 | D5: =IF(1<Assumptions!$B$26,Assumptions!$B$25,0) -> 20000 | E5: =(C5+D5)*(1+Assumptions!$B$12) -> 215040 | F5: =H4 -> 63000 | G5: =IF(1<Assumptions!$B$28,Assumptions!$B$27,0) -> 0 | H5: =(F5+G5)*(1+Assumptions!$B$12) -> 66150 | I5: =K4 -> 280350 | J5: =IF(1<Assumptions!$B$30,Assumptions!$B$29,0) -> 10000 | K5: =(I5+J5)*(1+Assumptions!$B$12) -> 304867.5
A6: =YEAR(TODAY())+2 -> 2028 | B6: =Assumptions!$B$4+2 -> 39 | C6: =E5 -> 215040 | D6: =IF(2<Assumptions!$B$26,Assumptions!$B$25,0) -> 20000 | E6: =(C6+D6)*(1+Assumptions!$B$12) -> 246792 | F6: =H5 -> 66150 | G6: =IF(2<Assumptions!$B$28,Assumptions!$B$27,0) -> 0 | H6: =(F6+G6)*(1+Assumptions!$B$12) -> 69457.5 | I6: =K5 -> 304867.5 | J6: =IF(2<Assumptions!$B$30,Assumptions!$B$29,0) -> 10000 | K6: =(I6+J6)*(1+Assumptions!$B$12) -> 330610.88
A7: =YEAR(TODAY())+3 -> 2029 | B7: =Assumptions!$B$4+3 -> 40 | C7: =E6 -> 246792 | D7: =IF(3<Assumptions!$B$26,Assumptions!$B$25,0) -> 0 | E7: =(C7+D7)*(1+Assumptions!$B$12) -> 259131.6 | F7: =H6 -> 69457.5 | G7: =IF(3<Assumptions!$B$28,Assumptions!$B$27,0) -> 0 | H7: =(F7+G7)*(1+Assumptions!$B$12) -> 72930.375 | I7: =K6 -> 330610.88 | J7: =IF(3<Assumptions!$B$30,Assumptions!$B$29,0) -> 10000 | K7: =(I7+J7)*(1+Assumptions!$B$12) -> 357641.42
A8: =YEAR(TODAY())+4 -> 2030 | B8: =Assumptions!$B$4+4 -> 41 | C8: =E7 -> 259131.6 | D8: =IF(4<Assumptions!$B$26,Assumptions!$B$25,0) -> 0 | E8: =(C8+D8)*(1+Assumptions!$B$12) -> 272088.18 | F8: =H7 -> 72930.375 | G8: =IF(4<Assumptions!$B$28,Assumptions!$B$27,0) -> 0 | H8: =(F8+G8)*(1+Assumptions!$B$12) -> 76576.894 | I8: =K7 -> 357641.42 | J8: =IF(4<Assumptions!$B$30,Assumptions!$B$29,0) -> 10000 | K8: =(I8+J8)*(1+Assumptions!$B$12) -> 386023.49
A9: =YEAR(TODAY())+5 -> 2031 | B9: =Assumptions!$B$4+5 -> 42 | C9: =E8 -> 272088.18 | D9: =IF(5<Assumptions!$B$26,Assumptions!$B$25,0) -> 0 | E9: =(C9+D9)*(1+Assumptions!$B$12) -> 285692.59 | F9: =H8 -> 76576.894 | G9: =IF(5<Assumptions!$B$28,Assumptions!$B$27,0) -> 0 | H9: =(F9+G9)*(1+Assumptions!$B$12) -> 80405.738 | I9: =K8 -> 386023.49 | J9: =IF(5<Assumptions!$B$30,Assumptions!$B$29,0) -> 10000 | K9: =(I9+J9)*(1+Assumptions!$B$12) -> 415824.66
A10: =YEAR(TODAY())+6 -> 2032 | B10: =Assumptions!$B$4+6 -> 43 | C10: =E9 -> 285692.59 | D10: =IF(6<Assumptions!$B$26,Assumptions!$B$25,0) -> 0 | E10: =(C10+D10)*(1+Assumptions!$B$12) -> 299977.22 | F10: =H9 -> 80405.738 | G10: =IF(6<Assumptions!$B$28,Assumptions!$B$27,0) -> 0 | H10: =(F10+G10)*(1+Assumptions!$B$12) -> 84426.025 | I10: =K9 -> 415824.66 | J10: =IF(6<Assumptions!$B$30,Assumptions!$B$29,0) -> 10000 | K10: =(I10+J10)*(1+Assumptions!$B$12) -> 447115.9
A11: =YEAR(TODAY())+7 -> 2033 | B11: =Assumptions!$B$4+7 -> 44 | C11: =E10 -> 299977.22 | D11: =IF(7<Assumptions!$B$26,Assumptions!$B$25,0) -> 0 | E11: =(C11+D11)*(1+Assumptions!$B$12) -> 314976.08 | F11: =H10 -> 84426.025 | G11: =IF(7<Assumptions!$B$28,Assumptions!$B$27,0) -> 0 | H11: =(F11+G11)*(1+Assumptions!$B$12) -> 88647.327 | I11: =K10 -> 447115.9 | J11: =IF(7<Assumptions!$B$30,Assumptions!$B$29,0) -> 10000 | K11: =(I11+J11)*(1+Assumptions!$B$12) -> 479971.69
A12: =YEAR(TODAY())+8 -> 2034 | B12: =Assumptions!$B$4+8 -> 45 | C12: =E11 -> 314976.08 | D12: =IF(8<Assumptions!$B$26,Assumptions!$B$25,0) -> 0 | E12: =(C12+D12)*(1+Assumptions!$B$12) -> 330724.88 | F12: =H11 -> 88647.327 | G12: =IF(8<Assumptions!$B$28,Assumptions!$B$27,0) -> 0 | H12: =(F12+G12)*(1+Assumptions!$B$12) -> 93079.693 | I12: =K11 -> 479971.69 | J12: =IF(8<Assumptions!$B$30,Assumptions!$B$29,0) -> 10000 | K12: =(I12+J12)*(1+Assumptions!$B$12) -> 514470.28
A13: =YEAR(TODAY())+9 -> 2035 | B13: =Assumptions!$B$4+9 -> 46 | C13: =E12 -> 330724.88 | D13: =IF(9<Assumptions!$B$26,Assumptions!$B$25,0) -> 0 | E13: =(C13+D13)*(1+Assumptions!$B$12) -> 347261.13 | F13: =H12 -> 93079.693 | G13: =IF(9<Assumptions!$B$28,Assumptions!$B$27,0) -> 0 | H13: =(F13+G13)*(1+Assumptions!$B$12) -> 97733.678 | I13: =K12 -> 514470.28 | J13: =IF(9<Assumptions!$B$30,Assumptions!$B$29,0) -> 10000 | K13: =(I13+J13)*(1+Assumptions!$B$12) -> 550693.79
A14: =YEAR(TODAY())+10 -> 2036 | B14: =Assumptions!$B$4+10 -> 47 | C14: =E13 -> 347261.13 | D14: =IF(10<Assumptions!$B$26,Assumptions!$B$25,0) -> 0 | E14: =(C14+D14)*(1+Assumptions!$B$12) -> 364624.18 | F14: =H13 -> 97733.678 | G14: =IF(10<Assumptions!$B$28,Assumptions!$B$27,0) -> 0 | H14: =(F14+G14)*(1+Assumptions!$B$12) -> 102620.36 | I14: =K13 -> 550693.79 | J14: =IF(10<Assumptions!$B$30,Assumptions!$B$29,0) -> 10000 | K14: =(I14+J14)*(1+Assumptions!$B$12) -> 588728.48
A15: =YEAR(TODAY())+11 -> 2037 | B15: =Assumptions!$B$4+11 -> 48 | C15: =E14 -> 364624.18 | D15: =IF(11<Assumptions!$B$26,Assumptions!$B$25,0) -> 0 | E15: =(C15+D15)*(1+Assumptions!$B$12) -> 382855.39 | F15: =H14 -> 102620.36 | G15: =IF(11<Assumptions!$B$28,Assumptions!$B$27,0) -> 0 | H15: =(F15+G15)*(1+Assumptions!$B$12) -> 107751.38 | I15: =K14 -> 588728.48 | J15: =IF(11<Assumptions!$B$30,Assumptions!$B$29,0) -> 10000 | K15: =(I15+J15)*(1+Assumptions!$B$12) -> 628664.9
A16: =YEAR(TODAY())+12 -> 2038 | B16: =Assumptions!$B$4+12 -> 49 | C16: =E15 -> 382855.39 | D16: =IF(12<Assumptions!$B$26,Assumptions!$B$25,0) -> 0 | E16: =(C16+D16)*(1+Assumptions!$B$12) -> 401998.16 | F16: =H15 -> 107751.38 | G16: =IF(12<Assumptions!$B$28,Assumptions!$B$27,0) -> 0 | H16: =(F16+G16)*(1+Assumptions!$B$12) -> 113138.95 | I16: =K15 -> 628664.9 | J16: =IF(12<Assumptions!$B$30,Assumptions!$B$29,0) -> 10000 | K16: =(I16+J16)*(1+Assumptions!$B$12) -> 670598.15
A17: =YEAR(TODAY())+13 -> 2039 | B17: =Assumptions!$B$4+13 -> 50 | C17: =E16 -> 401998.16 | D17: =IF(13<Assumptions!$B$26,Assumptions!$B$25,0) -> 0 | E17: =(C17+D17)*(1+Assumptions!$B$12) -> 422098.07 | F17: =H16 -> 113138.95 | G17: =IF(13<Assumptions!$B$28,Assumptions!$B$27,0) -> 0 | H17: =(F17+G17)*(1+Assumptions!$B$12) -> 118795.9 | I17: =K16 -> 670598.15 | J17: =IF(13<Assumptions!$B$30,Assumptions!$B$29,0) -> 0 | K17: =(I17+J17)*(1+Assumptions!$B$12) -> 704128.06
A19: Age 50 totals: | C19: ISA | E19: =E17 -> 422098.07 | F19: GIA | H19: =H17 -> 118795.9 | I19: SIPP | K19: =K17 -> 704128.06

Sheet Bridge to 57
A1: Bridge Phase — Age 50 to 57 (drawing down ISA+GIA for spending, SIPP coasting untouched)
A3: Year | B3: Age | C3: ISA+GIA Start | D3: Spending | E3: ISA+GIA End | F3: SIPP Start | G3: SIPP End
A4: =YEAR(TODAY())+13 -> 2039 | B4: =Assumptions!$B$4+13 -> 50 | C4: =Projection!$E$17+Projection!$H$17 -> 540893.97 | D4: =Assumptions!$B$13 -> 50000 | E4: =MAX(0,C4-D4)*(1+Assumptions!$B$12) -> 515438.67 | F4: =Projection!$K$17 -> 704128.06 | G4: =F4*(1+Assumptions!$B$12) -> 739334.46
A5: =YEAR(TODAY())+14 -> 2040 | B5: =Assumptions!$B$4+14 -> 51 | C5: =E4 -> 515438.67 | D5: =Assumptions!$B$13 -> 50000 | E5: =MAX(0,C5-D5)*(1+Assumptions!$B$12) -> 488710.6 | F5: =G4 -> 739334.46 | G5: =G4*(1+Assumptions!$B$12) -> 776301.18
A6: =YEAR(TODAY())+15 -> 2041 | B6: =Assumptions!$B$4+15 -> 52 | C6: =E5 -> 488710.6 | D6: =Assumptions!$B$13 -> 50000 | E6: =MAX(0,C6-D6)*(1+Assumptions!$B$12) -> 460646.13 | F6: =G5 -> 776301.18 | G6: =G5*(1+Assumptions!$B$12) -> 815116.24
A7: =YEAR(TODAY())+16 -> 2042 | B7: =Assumptions!$B$4+16 -> 53 | C7: =E6 -> 460646.13 | D7: =Assumptions!$B$13 -> 50000 | E7: =MAX(0,C7-D7)*(1+Assumptions!$B$12) -> 431178.43 | F7: =G6 -> 815116.24 | G7: =G6*(1+Assumptions!$B$12) -> 855872.05
A8: =YEAR(TODAY())+17 -> 2043 | B8: =Assumptions!$B$4+17 -> 54 | C8: =E7 -> 431178.43 | D8: =Assumptions!$B$13 -> 50000 | E8: =MAX(0,C8-D8)*(1+Assumptions!$B$12) -> 400237.36 | F8: =G7 -> 855872.05 | G8: =G7*(1+Assumptions!$B$12) -> 898665.66
A9: =YEAR(TODAY())+18 -> 2044 | B9: =Assumptions!$B$4+18 -> 55 | C9: =E8 -> 400237.36 | D9: =Assumptions!$B$13 -> 50000 | E9: =MAX(0,C9-D9)*(1+Assumptions!$B$12) -> 367749.22 | F9: =G8 -> 898665.66 | G9: =G8*(1+Assumptions!$B$12) -> 943598.94
A10: =YEAR(TODAY())+19 -> 2045 | B10: =Assumptions!$B$4+19 -> 56 | C10: =E9 -> 367749.22 | D10: =Assumptions!$B$13 -> 50000 | E10: =MAX(0,C10-D10)*(1+Assumptions!$B$12) -> 333636.69 | F10: =G9 -> 943598.94 | G10: =G9*(1+Assumptions!$B$12) -> 990778.89
A11: =YEAR(TODAY())+20 -> 2046 | B11: =Assumptions!$B$4+20 -> 57 | C11: =E10 -> 333636.69 | D11: =Assumptions!$B$13 -> 50000 | E11: =MAX(0,C11-D11)*(1+Assumptions!$B$12) -> 297818.52 | F11: =G10 -> 990778.89 | G11: =G10*(1+Assumptions!$B$12) -> 1040317.8
A13: At age 57: | C13: ISA+GIA remaining | E13: =E11 -> 297818.52 | F13: SIPP value | G13: =G11 -> 1040317.8

Sheet Summary
A1: Coast FIRE Summary
A3: Result
A4: ISA + GIA at age 50 | B4: =Projection!$E$17+Projection!$H$17 -> 540893.97 | C4: Your bridge-period pot
A5: SIPP at age 50 (still locked) | B5: =Projection!$K$17 -> 704128.06 | C5: Continues growing untouched until 57
A6: ISA+GIA remaining at age 57 (after 7yrs spending) | B6: ='Bridge to 57'!$E$11 -> 297818.52 | C6: Should be ≥ 0; if negative, bridge fails
A7: SIPP value at age 57 | B7: ='Bridge to 57'!$G$11 -> 1040317.8 | C7: Pot available to draw from age 57
A8: Sustainable income from SIPP at 57+ (at chosen SWR) | B8: ='Bridge to 57'!$G$11*Assumptions!$B$15 -> 36411.124 | C8: Using long-horizon safe withdrawal rate
A9: Sustainable income from SIPP + State Pension (67+) | B9: ='Bridge to 57'!$G$11*Assumptions!$B$15+Assumptions!$B$8 -> 47911.124 | C9: After state pension begins
A10: Target annual spend | B10: =Assumptions!$B$13 -> 50000 | C10: Your stated goal
A11: Shortfall / Surplus vs target (SIPP-only income, 57-67) | B11: ='Bridge to 57'!$G$11*Assumptions!$B$15-Assumptions!$B$13 -> -13588.876 | C11: Negative = shortfall, needs ISA top-up or lower spend
A13: How to use this model
A14: 1. Go to the Assumptions tab and adjust the yellow cells (years you plan to contribute to ISA/GIA/SIPP).
A15: 2. The Projection tab shows year-by-year growth from today to age 50.
A16: 3. The 'Bridge to 57' tab shows what happens as you spend down ISA+GIA between 50-57 while SIPP coasts.
A17: 4. This Summary tab shows whether you hit your target. Aim for the Shortfall/Surplus line to be ≥ £0.
A18: 5. Try reducing 'SIPP years you plan to contribute' until the shortfall just turns negative — that's your minimum.
